webapicontrollers/__init__.py
webapicontrollers/controllers/__init__.py
webapicontrollers/controllers/api_controller.py
webapicontrollers/di/__init__.py
webapicontrollers/di/di_container.py
webapicontrollers/enums/__init__.py
webapicontrollers/enums/http_methods.py
webapicontrollers/routing/__init__.py
webapicontrollers/routing/delete.py
webapicontrollers/routing/get.py
webapicontrollers/routing/head.py
webapicontrollers/routing/options.py
webapicontrollers/routing/patch.py
webapicontrollers/routing/post.py
webapicontrollers/routing/put.py
webapicontrollers/routing/registry.py
webapicontrollers/routing/route.py
webapicontrollers/routing/route_prefix.py
webapicontrollers-1.0.1.dist-info/METADATA
webapicontrollers-1.0.1.dist-info/WHEEL
webapicontrollers-1.0.1.dist-info/licenses/LICENSE
webapicontrollers-1.0.1.dist-info/RECORD
