Metadata-Version: 2.4
Name: webapicontrollers
Version: 1.0.1
Summary: A basic API controller framework built on top of FastAPI
Project-URL: Homepage, https://github.com/codingflowdev/web-api-controllers
Author: Coding Flow
License-File: LICENSE
Classifier: License :: OSI Approved :: MIT License
Classifier: Operating System :: OS Independent
Classifier: Programming Language :: Python :: 3
Requires-Python: >=3.8
Requires-Dist: annotated-types~=0.7.0
Requires-Dist: anyio~=4.9.0
Requires-Dist: click~=8.1.8
Requires-Dist: colorama~=0.4.6
Requires-Dist: fastapi~=0.115.12
Requires-Dist: h11~=0.16.0
Requires-Dist: idna~=3.10
Requires-Dist: pydantic-core~=2.33.2
Requires-Dist: pydantic~=2.11.4
Requires-Dist: sniffio~=1.3.1
Requires-Dist: starlette~=0.46.2
Requires-Dist: typing-extensions~=4.13.2
Requires-Dist: typing-inspection~=0.4.0
Requires-Dist: uvicorn~=0.34.2
